[
  {
    "id": 201, "priority": 1, "action": { "type": "block" },
    "condition": { "urlFilter": "||connect.facebook.net", "resourceTypes": ["script"] }
  },
  {
    "id": 202, "priority": 1, "action": { "type": "block" },
    "condition": { "urlFilter": "||doubleclick.net", "resourceTypes": ["script", "image"] }
  },
  {
    "id": 203, "priority": 1, "action": { "type": "block" },
    "condition": { "urlFilter": "||ad.doubleclick.net", "resourceTypes": ["script", "image"] }
  },
  {
    "id": 204, "priority": 1, "action": { "type": "block" },
    "condition": { "urlFilter": "||pagead2.googlesyndication.com", "resourceTypes": ["script", "image"] }
  },
  {
    "id": 205, "priority": 1, "action": { "type": "block" },
    "condition": { "urlFilter": "*://*.quantserve.com/*", "resourceTypes": ["script"] }
  },
  {
    "id": 206, "priority": 1, "action": { "type": "block" },
    "condition": { "urlFilter": "*://*.scorecardresearch.com/*", "resourceTypes": ["script"] }
  },
  {
    "id": 207, "priority": 1, "action": { "type": "block" },
    "condition": { "urlFilter": "*://*.mixpanel.com/*", "resourceTypes": ["script"] }
  },
  {
    "id": 208, "priority": 1, "action": { "type": "block" },
    "condition": { "urlFilter": "*://*.hotjar.com/*", "resourceTypes": ["script"] }
  },
  {
    "id": 209, "priority": 1, "action": { "type": "block" },
    "condition": { "urlFilter": "*://*.mouseflow.com/*", "resourceTypes": ["script"] }
  },
  {
    "id": 210, "priority": 1, "action": { "type": "block" },
    "condition": { "urlFilter": "*://*.fullstory.com/*", "resourceTypes": ["script"] }
  },
  {
    "id": 211, "priority": 1, "action": { "type": "block" },
    "condition": { "urlFilter": "*://*.clicktale.net/*", "resourceTypes": ["script"] }
  },
  {"id": 212, "priority": 1, "action": { "type": "block" },
    "condition": { "urlFilter": "*://*.yandex.ru/*", "resourceTypes": ["script"] }
  },
  {"id": 213, "priority": 1, "action": { "type": "block" },
    "condition": { "urlFilter": "*://*.yandex.net/*", "resourceTypes": ["script"] }
  },
  {"id": 214, "priority": 1, "action": { "type": "block" },
    "condition": { "urlFilter": "*://*.yandex.com/*", "resourceTypes": ["script"] }
  }
]